{
  "page": 19,
  "total_tokens": 199,
  "tokens": [
    {
      "text": "Neuberq@",
      "left": 112,
      "top": 89,
      "width": 464,
      "height": 76,
      "confidence": 63.0,
      "level": 5,
      "page_num": 1,
      "block_num": 1,
      "par_num": 1,
      "line_num": 1,
      "word_num": 1
    },
    {
      "text": "=",
      "left": 716,
      "top": 112,
      "width": 37,
      "height": 52,
      "confidence": 40.0,
      "level": 5,
      "page_num": 1,
      "block_num": 1,
      "par_num": 1,
      "line_num": 1,
      "word_num": 2
    },
    {
      "text": "BE",
      "left": 2024,
      "top": 128,
      "width": 87,
      "height": 37,
      "confidence": 50.0,
      "level": 5,
      "page_num": 1,
      "block_num": 1,
      "par_num": 1,
      "line_num": 1,
      "word_num": 3
    },
    {
      "text": "9g",
      "left": 413,
      "top": 106,
      "width": 51,
      "height": 109,
      "confidence": 75.0,
      "level": 5,
      "page_num": 1,
      "block_num": 1,
      "par_num": 1,
      "line_num": 2,
      "word_num": 1
    },
    {
      "text": "S",
      "left": 483,
      "top": 107,
      "width": 85,
      "height": 76,
      "confidence": 73.0,
      "level": 5,
      "page_num": 1,
      "block_num": 1,
      "par_num": 1,
      "line_num": 2,
      "word_num": 2
    },
    {
      "text": "Cea",
      "left": 1264,
      "top": 171,
      "width": 94,
      "height": 30,
      "confidence": 8.0,
      "level": 5,
      "page_num": 1,
      "block_num": 1,
      "par_num": 1,
      "line_num": 2,
      "word_num": 3
    },
    {
      "text": "ied",
      "left": 1386,
      "top": 166,
      "width": 38,
      "height": 49,
      "confidence": 29.0,
      "level": 5,
      "page_num": 1,
      "block_num": 1,
      "par_num": 1,
      "line_num": 2,
      "word_num": 4
    },
    {
      "text": "(es)",
      "left": 2014,
      "top": 127,
      "width": 119,
      "height": 113,
      "confidence": 40.0,
      "level": 5,
      "page_num": 1,
      "block_num": 1,
      "par_num": 1,
      "line_num": 2,
      "word_num": 5
    },
    {
      "text": "REFERENCE",
      "left": 220,
      "top": 209,
      "width": 233,
      "height": 21,
      "confidence": 94.0,
      "level": 5,
      "page_num": 1,
      "block_num": 1,
      "par_num": 1,
      "line_num": 3,
      "word_num": 1
    },
    {
      "text": "LABORATORY",
      "left": 488,
      "top": 209,
      "width": 268,
      "height": 20,
      "confidence": 96.0,
      "level": 5,
      "page_num": 1,
      "block_num": 1,
      "par_num": 1,
      "line_num": 3,
      "word_num": 2
    },
    {
      "text": "Para",
      "left": 1270,
      "top": 195,
      "width": 88,
      "height": 47,
      "confidence": 9.0,
      "level": 5,
      "page_num": 1,
      "block_num": 1,
      "par_num": 1,
      "line_num": 3,
      "word_num": 3
    },
    {
      "text": "ae",
      "left": 1380,
      "top": 195,
      "width": 39,
      "height": 44,
      "confidence": 20.0,
      "level": 5,
      "page_num": 1,
      "block_num": 1,
      "par_num": 1,
      "line_num": 3,
      "word_num": 4
    },
    {
      "text": "mice",
      "left": 1355,
      "top": 288,
      "width": 61,
      "height": 39,
      "confidence": 30.0,
      "level": 5,
      "page_num": 1,
      "block_num": 1,
      "par_num": 1,
      "line_num": 4,
      "word_num": 2
    },
    {
      "text": "MC-6072",
      "left": 2014,
      "top": 302,
      "width": 133,
      "height": 23,
      "confidence": 92.0,
      "level": 5,
      "page_num": 1,
      "block_num": 1,
      "par_num": 1,
      "line_num": 4,
      "word_num": 3
    },
    {
      "text": "LABORATORY",
      "left": 831,
      "top": 381,
      "width": 290,
      "height": 29,
      "confidence": 96.0,
      "level": 5,
      "page_num": 1,
      "block_num": 1,
      "par_num": 1,
      "line_num": 5,
      "word_num": 1
    },
    {
      "text": "REPORT",
      "left": 1137,
      "top": 381,
      "width": 171,
      "height": 29,
      "confidence": 91.0,
      "level": 5,
      "page_num": 1,
      "block_num": 1,
      "par_num": 1,
      "line_num": 5,
      "word_num": 2
    },
    {
      "text": "-",
      "left": 1334,
      "top": 397,
      "width": 11,
      "height": 4,
      "confidence": 64.0,
      "level": 5,
      "page_num": 1,
      "block_num": 1,
      "par_num": 1,
      "line_num": 5,
      "word_num": 3
    },
    {
      "text": "FINAL",
      "left": 1377,
      "top": 381,
      "width": 119,
      "height": 29,
      "confidence": 96.0,
      "level": 5,
      "page_num": 1,
      "block_num": 1,
      "par_num": 1,
      "line_num": 5,
      "word_num": 4
    },
    {
      "text": "LANA",
      "left": 1880,
      "top": 355,
      "width": 299,
      "height": 84,
      "confidence": 28.0,
      "level": 5,
      "page_num": 1,
      "block_num": 1,
      "par_num": 1,
      "line_num": 5,
      "word_num": 5
    },
    {
      "text": "Name",
      "left": 164,
      "top": 464,
      "width": 98,
      "height": 26,
      "confidence": 50.0,
      "level": 5,
      "page_num": 1,
      "block_num": 1,
      "par_num": 1,
      "line_num": 6,
      "word_num": 1
    },
    {
      "text": "_",
      "left": 269,
      "top": 460,
      "width": 4,
      "height": 41,
      "confidence": 50.0,
      "level": 5,
      "page_num": 1,
      "block_num": 1,
      "par_num": 1,
      "line_num": 6,
      "word_num": 2
    },
    {
      "text": ":",
      "left": 298,
      "top": 470,
      "width": 5,
      "height": 20,
      "confidence": 88.0,
      "level": 5,
      "page_num": 1,
      "block_num": 1,
      "par_num": 1,
      "line_num": 6,
      "word_num": 3
    },
    {
      "text": "Mrs",
      "left": 322,
      "top": 464,
      "width": 63,
      "height": 26,
      "confidence": 91.0,
      "level": 5,
      "page_num": 1,
      "block_num": 1,
      "par_num": 1,
      "line_num": 6,
      "word_num": 4
    },
    {
      "text": "RATHNA",
      "left": 399,
      "top": 464,
      "width": 155,
      "height": 26,
      "confidence": 90.0,
      "level": 5,
      "page_num": 1,
      "block_num": 1,
      "par_num": 1,
      "line_num": 6,
      "word_num": 5
    },
    {
      "text": "GABRIAL",
      "left": 567,
      "top": 464,
      "width": 169,
      "height": 26,
      "confidence": 91.0,
      "level": 5,
      "page_num": 1,
      "block_num": 1,
      "par_num": 1,
      "line_num": 6,
      "word_num": 6
    },
    {
      "text": "Gender",
      "left": 1245,
      "top": 463,
      "width": 130,
      "height": 27,
      "confidence": 42.0,
      "level": 5,
      "page_num": 1,
      "block_num": 1,
      "par_num": 1,
      "line_num": 6,
      "word_num": 7
    },
    {
      "text": ":",
      "left": 1428,
      "top": 470,
      "width": 4,
      "height": 20,
      "confidence": 66.0,
      "level": 5,
      "page_num": 1,
      "block_num": 1,
      "par_num": 1,
      "line_num": 6,
      "word_num": 8
    },
    {
      "text": "Female",
      "left": 1455,
      "top": 463,
      "width": 121,
      "height": 28,
      "confidence": 96.0,
      "level": 5,
      "page_num": 1,
      "block_num": 1,
      "par_num": 1,
      "line_num": 6,
      "word_num": 9
    },
    {
      "text": "LabID",
      "left": 1836,
      "top": 463,
      "width": 111,
      "height": 27,
      "confidence": 61.0,
      "level": 5,
      "page_num": 1,
      "block_num": 1,
      "par_num": 1,
      "line_num": 6,
      "word_num": 10
    },
    {
      "text": ":",
      "left": 1994,
      "top": 470,
      "width": 5,
      "height": 20,
      "confidence": 61.0,
      "level": 5,
      "page_num": 1,
      "block_num": 1,
      "par_num": 1,
      "line_num": 6,
      "word_num": 11
    },
    {
      "text": "50636000175",
      "left": 2020,
      "top": 464,
      "width": 226,
      "height": 26,
      "confidence": 96.0,
      "level": 5,
      "page_num": 1,
      "block_num": 1,
      "par_num": 1,
      "line_num": 6,
      "word_num": 12
    },
    {
      "text": "Age’:",
      "left": 163,
      "top": 526,
      "width": 140,
      "height": 34,
      "confidence": 17.0,
      "level": 5,
      "page_num": 1,
      "block_num": 1,
      "par_num": 1,
      "line_num": 7,
      "word_num": 1
    },
    {
      "text": "79",
      "left": 321,
      "top": 526,
      "width": 39,
      "height": 26,
      "confidence": 83.0,
      "level": 5,
      "page_num": 1,
      "block_num": 1,
      "par_num": 1,
      "line_num": 7,
      "word_num": 2
    },
    {
      "text": "Years",
      "left": 372,
      "top": 526,
      "width": 100,
      "height": 26,
      "confidence": 94.0,
      "level": 5,
      "page_num": 1,
      "block_num": 1,
      "par_num": 1,
      "line_num": 7,
      "word_num": 3
    },
    {
      "text": "Mob.",
      "left": 1246,
      "top": 525,
      "width": 83,
      "height": 27,
      "confidence": 96.0,
      "level": 5,
      "page_num": 1,
      "block_num": 1,
      "par_num": 1,
      "line_num": 7,
      "word_num": 4
    },
    {
      "text": "No.",
      "left": 1344,
      "top": 526,
      "width": 56,
      "height": 26,
      "confidence": 92.0,
      "level": 5,
      "page_num": 1,
      "block_num": 1,
      "par_num": 1,
      "line_num": 7,
      "word_num": 5
    },
    {
      "text": ":",
      "left": 1428,
      "top": 532,
      "width": 4,
      "height": 20,
      "confidence": 92.0,
      "level": 5,
      "page_num": 1,
      "block_num": 1,
      "par_num": 1,
      "line_num": 7,
      "word_num": 6
    },
    {
      "text": "EMAMI",
      "left": 323,
      "top": 589,
      "width": 117,
      "height": 26,
      "confidence": 91.0,
      "level": 5,
      "page_num": 1,
      "block_num": 1,
      "par_num": 1,
      "line_num": 8,
      "word_num": 3
    },
    {
      "text": "FRANK",
      "left": 456,
      "top": 589,
      "width": 123,
      "height": 26,
      "confidence": 96.0,
      "level": 5,
      "page_num": 1,
      "block_num": 1,
      "par_num": 1,
      "line_num": 8,
      "word_num": 4
    },
    {
      "text": "ROSS",
      "left": 593,
      "top": 589,
      "width": 102,
      "height": 26,
      "confidence": 96.0,
      "level": 5,
      "page_num": 1,
      "block_num": 1,
      "par_num": 1,
      "line_num": 8,
      "word_num": 5
    },
    {
      "text": "LIMITED",
      "left": 710,
      "top": 589,
      "width": 144,
      "height": 26,
      "confidence": 96.0,
      "level": 5,
      "page_num": 1,
      "block_num": 1,
      "par_num": 1,
      "line_num": 8,
      "word_num": 6
    },
    {
      "text": "Ref.By",
      "left": 1246,
      "top": 588,
      "width": 127,
      "height": 35,
      "confidence": 70.0,
      "level": 5,
      "page_num": 1,
      "block_num": 1,
      "par_num": 1,
      "line_num": 8,
      "word_num": 7
    },
    {
      "text": ":",
      "left": 1428,
      "top": 597,
      "width": 5,
      "height": 22,
      "confidence": 70.0,
      "level": 5,
      "page_num": 1,
      "block_num": 1,
      "par_num": 1,
      "line_num": 8,
      "word_num": 8
    },
    {
      "text": "Pit.Loc",
      "left": 1836,
      "top": 589,
      "width": 121,
      "height": 26,
      "confidence": 47.0,
      "level": 5,
      "page_num": 1,
      "block_num": 1,
      "par_num": 1,
      "line_num": 8,
      "word_num": 9
    },
    {
      "text": ":",
      "left": 1994,
      "top": 595,
      "width": 5,
      "height": 20,
      "confidence": 86.0,
      "level": 5,
      "page_num": 1,
      "block_num": 1,
      "par_num": 1,
      "line_num": 8,
      "word_num": 10
    },
    {
      "text": "Reg",
      "left": 164,
      "top": 657,
      "width": 65,
      "height": 34,
      "confidence": 96.0,
      "level": 5,
      "page_num": 1,
      "block_num": 1,
      "par_num": 1,
      "line_num": 9,
      "word_num": 1
    },
    {
      "text": "Date",
      "left": 245,
      "top": 657,
      "width": 77,
      "height": 26,
      "confidence": 96.0,
      "level": 5,
      "page_num": 1,
      "block_num": 1,
      "par_num": 1,
      "line_num": 9,
      "word_num": 2
    },
    {
      "text": "and",
      "left": 334,
      "top": 656,
      "width": 64,
      "height": 27,
      "confidence": 96.0,
      "level": 5,
      "page_num": 1,
      "block_num": 1,
      "par_num": 1,
      "line_num": 9,
      "word_num": 3
    },
    {
      "text": "Time",
      "left": 412,
      "top": 656,
      "width": 85,
      "height": 27,
      "confidence": 86.0,
      "level": 5,
      "page_num": 1,
      "block_num": 1,
      "par_num": 1,
      "line_num": 9,
      "word_num": 4
    },
    {
      "text": "03-Jun-2025",
      "left": 584,
      "top": 657,
      "width": 207,
      "height": 26,
      "confidence": 96.0,
      "level": 5,
      "page_num": 1,
      "block_num": 1,
      "par_num": 1,
      "line_num": 9,
      "word_num": 7
    },
    {
      "text": "08:37",
      "left": 805,
      "top": 657,
      "width": 91,
      "height": 27,
      "confidence": 96.0,
      "level": 5,
      "page_num": 1,
      "block_num": 1,
      "par_num": 1,
      "line_num": 9,
      "word_num": 8
    },
    {
      "text": "Report",
      "left": 974,
      "top": 657,
      "width": 118,
      "height": 34,
      "confidence": 96.0,
      "level": 5,
      "page_num": 1,
      "block_num": 1,
      "par_num": 1,
      "line_num": 9,
      "word_num": 9
    },
    {
      "text": "Date",
      "left": 1105,
      "top": 657,
      "width": 77,
      "height": 26,
      "confidence": 96.0,
      "level": 5,
      "page_num": 1,
      "block_num": 1,
      "par_num": 1,
      "line_num": 9,
      "word_num": 10
    },
    {
      "text": "and",
      "left": 1194,
      "top": 656,
      "width": 64,
      "height": 27,
      "confidence": 95.0,
      "level": 5,
      "page_num": 1,
      "block_num": 1,
      "par_num": 1,
      "line_num": 9,
      "word_num": 11
    },
    {
      "text": "Time",
      "left": 1272,
      "top": 656,
      "width": 85,
      "height": 27,
      "confidence": 59.0,
      "level": 5,
      "page_num": 1,
      "block_num": 1,
      "par_num": 1,
      "line_num": 9,
      "word_num": 12
    },
    {
      "text": ":",
      "left": 1393,
      "top": 663,
      "width": 4,
      "height": 20,
      "confidence": 59.0,
      "level": 5,
      "page_num": 1,
      "block_num": 1,
      "par_num": 1,
      "line_num": 9,
      "word_num": 13
    },
    {
      "text": "03-Jun-2025",
      "left": 1419,
      "top": 657,
      "width": 207,
      "height": 26,
      "confidence": 79.0,
      "level": 5,
      "page_num": 1,
      "block_num": 1,
      "par_num": 1,
      "line_num": 9,
      "word_num": 14
    },
    {
      "text": "11:41",
      "left": 1640,
      "top": 657,
      "width": 90,
      "height": 26,
      "confidence": 79.0,
      "level": 5,
      "page_num": 1,
      "block_num": 1,
      "par_num": 1,
      "line_num": 9,
      "word_num": 15
    },
    {
      "text": "Refidi",
      "left": 1771,
      "top": 656,
      "width": 122,
      "height": 27,
      "confidence": 49.0,
      "level": 5,
      "page_num": 1,
      "block_num": 1,
      "par_num": 1,
      "line_num": 9,
      "word_num": 16
    },
    {
      "text": ":",
      "left": 1928,
      "top": 663,
      "width": 4,
      "height": 20,
      "confidence": 89.0,
      "level": 5,
      "page_num": 1,
      "block_num": 1,
      "par_num": 1,
      "line_num": 9,
      "word_num": 17
    },
    {
      "text": "Sample",
      "left": 162,
      "top": 718,
      "width": 131,
      "height": 35,
      "confidence": 96.0,
      "level": 5,
      "page_num": 1,
      "block_num": 1,
      "par_num": 1,
      "line_num": 10,
      "word_num": 1
    },
    {
      "text": "Received",
      "left": 307,
      "top": 718,
      "width": 160,
      "height": 27,
      "confidence": 95.0,
      "level": 5,
      "page_num": 1,
      "block_num": 1,
      "par_num": 1,
      "line_num": 10,
      "word_num": 2
    },
    {
      "text": "at",
      "left": 480,
      "top": 720,
      "width": 33,
      "height": 25,
      "confidence": 45.0,
      "level": 5,
      "page_num": 1,
      "block_num": 1,
      "par_num": 1,
      "line_num": 10,
      "word_num": 3
    },
    {
      "text": ":",
      "left": 558,
      "top": 725,
      "width": 5,
      "height": 20,
      "confidence": 47.0,
      "level": 5,
      "page_num": 1,
      "block_num": 1,
      "par_num": 1,
      "line_num": 10,
      "word_num": 4
    },
    {
      "text": "KA-Kasturinagar",
      "left": 585,
      "top": 717,
      "width": 272,
      "height": 36,
      "confidence": 92.0,
      "level": 5,
      "page_num": 1,
      "block_num": 1,
      "par_num": 1,
      "line_num": 10,
      "word_num": 5
    },
    {
      "text": "Refld2",
      "left": 1771,
      "top": 718,
      "width": 121,
      "height": 27,
      "confidence": 54.0,
      "level": 5,
      "page_num": 1,
      "block_num": 1,
      "par_num": 1,
      "line_num": 10,
      "word_num": 6
    },
    {
      "text": ":",
      "left": 1928,
      "top": 725,
      "width": 4,
      "height": 20,
      "confidence": 87.0,
      "level": 5,
      "page_num": 1,
      "block_num": 1,
      "par_num": 1,
      "line_num": 10,
      "word_num": 7
    },
    {
      "text": "Sample",
      "left": 162,
      "top": 778,
      "width": 131,
      "height": 35,
      "confidence": 96.0,
      "level": 5,
      "page_num": 1,
      "block_num": 1,
      "par_num": 1,
      "line_num": 11,
      "word_num": 1
    },
    {
      "text": "Collected",
      "left": 306,
      "top": 778,
      "width": 165,
      "height": 27,
      "confidence": 95.0,
      "level": 5,
      "page_num": 1,
      "block_num": 1,
      "par_num": 1,
      "line_num": 11,
      "word_num": 2
    },
    {
      "text": "at:",
      "left": 484,
      "top": 780,
      "width": 79,
      "height": 25,
      "confidence": 7.0,
      "level": 5,
      "page_num": 1,
      "block_num": 1,
      "par_num": 1,
      "line_num": 11,
      "word_num": 3
    },
    {
      "text": "TEST",
      "left": 163,
      "top": 932,
      "width": 95,
      "height": 26,
      "confidence": 95.0,
      "level": 5,
      "page_num": 1,
      "block_num": 1,
      "par_num": 1,
      "line_num": 12,
      "word_num": 1
    },
    {
      "text": "RESULTS",
      "left": 863,
      "top": 932,
      "width": 169,
      "height": 26,
      "confidence": 96.0,
      "level": 5,
      "page_num": 1,
      "block_num": 1,
      "par_num": 1,
      "line_num": 12,
      "word_num": 2
    },
    {
      "text": "UNIT",
      "left": 1217,
      "top": 932,
      "width": 84,
      "height": 26,
      "confidence": 96.0,
      "level": 5,
      "page_num": 1,
      "block_num": 1,
      "par_num": 1,
      "line_num": 12,
      "word_num": 3
    },
    {
      "text": "BIOLOGICAL",
      "left": 1440,
      "top": 932,
      "width": 224,
      "height": 26,
      "confidence": 96.0,
      "level": 5,
      "page_num": 1,
      "block_num": 1,
      "par_num": 1,
      "line_num": 12,
      "word_num": 4
    },
    {
      "text": "REF",
      "left": 1678,
      "top": 932,
      "width": 71,
      "height": 26,
      "confidence": 96.0,
      "level": 5,
      "page_num": 1,
      "block_num": 1,
      "par_num": 1,
      "line_num": 12,
      "word_num": 5
    },
    {
      "text": "RANGE",
      "left": 1763,
      "top": 932,
      "width": 130,
      "height": 26,
      "confidence": 95.0,
      "level": 5,
      "page_num": 1,
      "block_num": 1,
      "par_num": 1,
      "line_num": 12,
      "word_num": 6
    },
    {
      "text": "REMARKS",
      "left": 1922,
      "top": 932,
      "width": 181,
      "height": 26,
      "confidence": 96.0,
      "level": 5,
      "page_num": 1,
      "block_num": 1,
      "par_num": 1,
      "line_num": 12,
      "word_num": 7
    },
    {
      "text": "Plasma",
      "left": 166,
      "top": 1023,
      "width": 122,
      "height": 28,
      "confidence": 96.0,
      "level": 5,
      "page_num": 1,
      "block_num": 1,
      "par_num": 1,
      "line_num": 13,
      "word_num": 1
    },
    {
      "text": "Glucose",
      "left": 300,
      "top": 1022,
      "width": 134,
      "height": 29,
      "confidence": 92.0,
      "level": 5,
      "page_num": 1,
      "block_num": 1,
      "par_num": 1,
      "line_num": 13,
      "word_num": 2
    },
    {
      "text": "-",
      "left": 447,
      "top": 1038,
      "width": 10,
      "height": 4,
      "confidence": 90.0,
      "level": 5,
      "page_num": 1,
      "block_num": 1,
      "par_num": 1,
      "line_num": 13,
      "word_num": 3
    },
    {
      "text": "F",
      "left": 472,
      "top": 1024,
      "width": 19,
      "height": 26,
      "confidence": 90.0,
      "level": 5,
      "page_num": 1,
      "block_num": 1,
      "par_num": 1,
      "line_num": 13,
      "word_num": 4
    },
    {
      "text": "102",
      "left": 861,
      "top": 1024,
      "width": 58,
      "height": 26,
      "confidence": 96.0,
      "level": 5,
      "page_num": 1,
      "block_num": 1,
      "par_num": 1,
      "line_num": 13,
      "word_num": 5
    },
    {
      "text": "mg/dL",
      "left": 1229,
      "top": 1022,
      "width": 102,
      "height": 36,
      "confidence": 79.0,
      "level": 5,
      "page_num": 1,
      "block_num": 1,
      "par_num": 1,
      "line_num": 13,
      "word_num": 6
    },
    {
      "text": "</=",
      "left": 1455,
      "top": 1022,
      "width": 51,
      "height": 29,
      "confidence": 92.0,
      "level": 5,
      "page_num": 1,
      "block_num": 1,
      "par_num": 1,
      "line_num": 13,
      "word_num": 7
    },
    {
      "text": "100",
      "left": 1520,
      "top": 1024,
      "width": 59,
      "height": 26,
      "confidence": 96.0,
      "level": 5,
      "page_num": 1,
      "block_num": 1,
      "par_num": 1,
      "line_num": 13,
      "word_num": 8
    },
    {
      "text": "mg/dl:",
      "left": 1593,
      "top": 1022,
      "width": 97,
      "height": 36,
      "confidence": 92.0,
      "level": 5,
      "page_num": 1,
      "block_num": 1,
      "par_num": 1,
      "line_num": 13,
      "word_num": 9
    },
    {
      "text": "Normal",
      "left": 1706,
      "top": 1023,
      "width": 116,
      "height": 28,
      "confidence": 96.0,
      "level": 5,
      "page_num": 1,
      "block_num": 1,
      "par_num": 1,
      "line_num": 13,
      "word_num": 10
    },
    {
      "text": "HEXOKINASE/G-6-PDH",
      "left": 164,
      "top": 1069,
      "width": 317,
      "height": 46,
      "confidence": 92.0,
      "level": 5,
      "page_num": 1,
      "block_num": 1,
      "par_num": 1,
      "line_num": 14,
      "word_num": 1
    },
    {
      "text": "100",
      "left": 1456,
      "top": 1066,
      "width": 58,
      "height": 26,
      "confidence": 91.0,
      "level": 5,
      "page_num": 1,
      "block_num": 1,
      "par_num": 1,
      "line_num": 14,
      "word_num": 2
    },
    {
      "text": "-",
      "left": 1527,
      "top": 1080,
      "width": 12,
      "height": 30,
      "confidence": 91.0,
      "level": 5,
      "page_num": 1,
      "block_num": 1,
      "par_num": 1,
      "line_num": 14,
      "word_num": 3
    },
    {
      "text": "125",
      "left": 1552,
      "top": 1066,
      "width": 58,
      "height": 26,
      "confidence": 96.0,
      "level": 5,
      "page_num": 1,
      "block_num": 1,
      "par_num": 1,
      "line_num": 14,
      "word_num": 4
    },
    {
      "text": "mg/dl:",
      "left": 1624,
      "top": 1064,
      "width": 97,
      "height": 36,
      "confidence": 89.0,
      "level": 5,
      "page_num": 1,
      "block_num": 1,
      "par_num": 1,
      "line_num": 14,
      "word_num": 5
    },
    {
      "text": "Prediabetes",
      "left": 1456,
      "top": 1106,
      "width": 196,
      "height": 29,
      "confidence": 93.0,
      "level": 5,
      "page_num": 1,
      "block_num": 1,
      "par_num": 1,
      "line_num": 15,
      "word_num": 1
    },
    {
      "text": ">/=",
      "left": 1455,
      "top": 1147,
      "width": 51,
      "height": 29,
      "confidence": 92.0,
      "level": 5,
      "page_num": 1,
      "block_num": 1,
      "par_num": 1,
      "line_num": 16,
      "word_num": 1
    },
    {
      "text": "126",
      "left": 1520,
      "top": 1149,
      "width": 59,
      "height": 26,
      "confidence": 96.0,
      "level": 5,
      "page_num": 1,
      "block_num": 1,
      "par_num": 1,
      "line_num": 16,
      "word_num": 2
    },
    {
      "text": "mg/dl:",
      "left": 1593,
      "top": 1147,
      "width": 97,
      "height": 36,
      "confidence": 93.0,
      "level": 5,
      "page_num": 1,
      "block_num": 1,
      "par_num": 1,
      "line_num": 16,
      "word_num": 3
    },
    {
      "text": "Diabetes.",
      "left": 1706,
      "top": 1147,
      "width": 153,
      "height": 29,
      "confidence": 96.0,
      "level": 5,
      "page_num": 1,
      "block_num": 1,
      "par_num": 1,
      "line_num": 16,
      "word_num": 4
    },
    {
      "text": "(By",
      "left": 1455,
      "top": 1189,
      "width": 54,
      "height": 36,
      "confidence": 96.0,
      "level": 5,
      "page_num": 1,
      "block_num": 1,
      "par_num": 1,
      "line_num": 17,
      "word_num": 1
    },
    {
      "text": "the",
      "left": 1520,
      "top": 1189,
      "width": 51,
      "height": 29,
      "confidence": 96.0,
      "level": 5,
      "page_num": 1,
      "block_num": 1,
      "par_num": 1,
      "line_num": 17,
      "word_num": 2
    },
    {
      "text": "ADA",
      "left": 1583,
      "top": 1191,
      "width": 76,
      "height": 26,
      "confidence": 95.0,
      "level": 5,
      "page_num": 1,
      "block_num": 1,
      "par_num": 1,
      "line_num": 17,
      "word_num": 3
    },
    {
      "text": "Recommendation",
      "left": 1456,
      "top": 1231,
      "width": 289,
      "height": 29,
      "confidence": 92.0,
      "level": 5,
      "page_num": 1,
      "block_num": 1,
      "par_num": 1,
      "line_num": 18,
      "word_num": 1
    },
    {
      "text": "-",
      "left": 1759,
      "top": 1247,
      "width": 10,
      "height": 4,
      "confidence": 92.0,
      "level": 5,
      "page_num": 1,
      "block_num": 1,
      "par_num": 1,
      "line_num": 18,
      "word_num": 2
    },
    {
      "text": "Jan",
      "left": 1781,
      "top": 1233,
      "width": 58,
      "height": 27,
      "confidence": 96.0,
      "level": 5,
      "page_num": 1,
      "block_num": 1,
      "par_num": 1,
      "line_num": 18,
      "word_num": 3
    },
    {
      "text": "2012)",
      "left": 1455,
      "top": 1272,
      "width": 92,
      "height": 36,
      "confidence": 96.0,
      "level": 5,
      "page_num": 1,
      "block_num": 1,
      "par_num": 1,
      "line_num": 19,
      "word_num": 1
    },
    {
      "text": "Plasma",
      "left": 164,
      "top": 1335,
      "width": 95,
      "height": 22,
      "confidence": 96.0,
      "level": 5,
      "page_num": 1,
      "block_num": 1,
      "par_num": 1,
      "line_num": 20,
      "word_num": 1
    },
    {
      "text": "Fluoride",
      "left": 269,
      "top": 1334,
      "width": 103,
      "height": 23,
      "confidence": 93.0,
      "level": 5,
      "page_num": 1,
      "block_num": 1,
      "par_num": 1,
      "line_num": 20,
      "word_num": 2
    },
    {
      "text": "F",
      "left": 383,
      "top": 1336,
      "width": 15,
      "height": 20,
      "confidence": 91.0,
      "level": 5,
      "page_num": 1,
      "block_num": 1,
      "par_num": 1,
      "line_num": 20,
      "word_num": 3
    },
    {
      "text": "Coll.",
      "left": 567,
      "top": 1335,
      "width": 55,
      "height": 22,
      "confidence": 91.0,
      "level": 5,
      "page_num": 1,
      "block_num": 1,
      "par_num": 1,
      "line_num": 20,
      "word_num": 4
    },
    {
      "text": "Time:03-Jun-2025",
      "left": 632,
      "top": 1334,
      "width": 236,
      "height": 23,
      "confidence": 91.0,
      "level": 5,
      "page_num": 1,
      "block_num": 1,
      "par_num": 1,
      "line_num": 20,
      "word_num": 5
    },
    {
      "text": "08:45",
      "left": 878,
      "top": 1335,
      "width": 71,
      "height": 22,
      "confidence": 96.0,
      "level": 5,
      "page_num": 1,
      "block_num": 1,
      "par_num": 1,
      "line_num": 20,
      "word_num": 6
    },
    {
      "text": "Potassium",
      "left": 166,
      "top": 1387,
      "width": 170,
      "height": 45,
      "confidence": 96.0,
      "level": 5,
      "page_num": 1,
      "block_num": 1,
      "par_num": 1,
      "line_num": 21,
      "word_num": 1
    },
    {
      "text": "4.57",
      "left": 859,
      "top": 1393,
      "width": 71,
      "height": 26,
      "confidence": 96.0,
      "level": 5,
      "page_num": 1,
      "block_num": 1,
      "par_num": 1,
      "line_num": 21,
      "word_num": 2
    },
    {
      "text": "mEq/L",
      "left": 1229,
      "top": 1391,
      "width": 106,
      "height": 36,
      "confidence": 85.0,
      "level": 5,
      "page_num": 1,
      "block_num": 1,
      "par_num": 1,
      "line_num": 21,
      "word_num": 3
    },
    {
      "text": "3.5-5.1",
      "left": 1455,
      "top": 1393,
      "width": 134,
      "height": 26,
      "confidence": 91.0,
      "level": 5,
      "page_num": 1,
      "block_num": 1,
      "par_num": 1,
      "line_num": 21,
      "word_num": 4
    },
    {
      "text": "ISE,",
      "left": 164,
      "top": 1452,
      "width": 51,
      "height": 25,
      "confidence": 91.0,
      "level": 5,
      "page_num": 1,
      "block_num": 1,
      "par_num": 1,
      "line_num": 22,
      "word_num": 1
    },
    {
      "text": "Indirect",
      "left": 227,
      "top": 1451,
      "width": 96,
      "height": 23,
      "confidence": 87.0,
      "level": 5,
      "page_num": 1,
      "block_num": 1,
      "par_num": 1,
      "line_num": 22,
      "word_num": 2
    },
    {
      "text": "Serum",
      "left": 163,
      "top": 1506,
      "width": 83,
      "height": 22,
      "confidence": 96.0,
      "level": 5,
      "page_num": 1,
      "block_num": 1,
      "par_num": 1,
      "line_num": 23,
      "word_num": 1
    },
    {
      "text": "Coll.",
      "left": 567,
      "top": 1505,
      "width": 55,
      "height": 22,
      "confidence": 91.0,
      "level": 5,
      "page_num": 1,
      "block_num": 1,
      "par_num": 1,
      "line_num": 23,
      "word_num": 2
    },
    {
      "text": "Time:03-Jun-2025",
      "left": 632,
      "top": 1504,
      "width": 236,
      "height": 23,
      "confidence": 91.0,
      "level": 5,
      "page_num": 1,
      "block_num": 1,
      "par_num": 1,
      "line_num": 23,
      "word_num": 3
    },
    {
      "text": "08:45",
      "left": 878,
      "top": 1505,
      "width": 71,
      "height": 22,
      "confidence": 96.0,
      "level": 5,
      "page_num": 1,
      "block_num": 1,
      "par_num": 1,
      "line_num": 23,
      "word_num": 4
    },
    {
      "text": "Approved",
      "left": 163,
      "top": 1651,
      "width": 140,
      "height": 31,
      "confidence": 96.0,
      "level": 5,
      "page_num": 1,
      "block_num": 1,
      "par_num": 1,
      "line_num": 24,
      "word_num": 1
    },
    {
      "text": "By:",
      "left": 317,
      "top": 1652,
      "width": 43,
      "height": 30,
      "confidence": 95.0,
      "level": 5,
      "page_num": 1,
      "block_num": 1,
      "par_num": 1,
      "line_num": 24,
      "word_num": 2
    },
    {
      "text": "DR",
      "left": 403,
      "top": 1652,
      "width": 44,
      "height": 23,
      "confidence": 88.0,
      "level": 5,
      "page_num": 1,
      "block_num": 1,
      "par_num": 1,
      "line_num": 24,
      "word_num": 3
    },
    {
      "text": "Prajwal",
      "left": 460,
      "top": 1650,
      "width": 105,
      "height": 32,
      "confidence": 92.0,
      "level": 5,
      "page_num": 1,
      "block_num": 1,
      "par_num": 1,
      "line_num": 24,
      "word_num": 4
    },
    {
      "text": "A",
      "left": 577,
      "top": 1652,
      "width": 22,
      "height": 23,
      "confidence": 96.0,
      "level": 5,
      "page_num": 1,
      "block_num": 1,
      "par_num": 1,
      "line_num": 24,
      "word_num": 5
    },
    {
      "text": "Released",
      "left": 165,
      "top": 1685,
      "width": 136,
      "height": 25,
      "confidence": 96.0,
      "level": 5,
      "page_num": 1,
      "block_num": 1,
      "par_num": 1,
      "line_num": 25,
      "word_num": 1
    },
    {
      "text": "by:",
      "left": 315,
      "top": 1685,
      "width": 39,
      "height": 31,
      "confidence": 90.0,
      "level": 5,
      "page_num": 1,
      "block_num": 1,
      "par_num": 1,
      "line_num": 25,
      "word_num": 2
    },
    {
      "text": "Neuberg",
      "left": 369,
      "top": 1685,
      "width": 123,
      "height": 31,
      "confidence": 90.0,
      "level": 5,
      "page_num": 1,
      "block_num": 1,
      "par_num": 1,
      "line_num": 25,
      "word_num": 3
    },
    {
      "text": "Anand",
      "left": 504,
      "top": 1685,
      "width": 94,
      "height": 25,
      "confidence": 96.0,
      "level": 5,
      "page_num": 1,
      "block_num": 1,
      "par_num": 1,
      "line_num": 25,
      "word_num": 4
    },
    {
      "text": "Reference",
      "left": 611,
      "top": 1685,
      "width": 151,
      "height": 25,
      "confidence": 96.0,
      "level": 5,
      "page_num": 1,
      "block_num": 1,
      "par_num": 1,
      "line_num": 25,
      "word_num": 5
    },
    {
      "text": "Laboratory",
      "left": 774,
      "top": 1685,
      "width": 157,
      "height": 31,
      "confidence": 96.0,
      "level": 5,
      "page_num": 1,
      "block_num": 1,
      "par_num": 1,
      "line_num": 25,
      "word_num": 6
    },
    {
      "text": "Note:(LL-VeryLow,L-Low,H-High,",
      "left": 176,
      "top": 2845,
      "width": 425,
      "height": 37,
      "confidence": 83.0,
      "level": 5,
      "page_num": 1,
      "block_num": 1,
      "par_num": 1,
      "line_num": 26,
      "word_num": 1
    },
    {
      "text": "HH-VeryHigh,A-Abnormal,HC-",
      "left": 619,
      "top": 2845,
      "width": 374,
      "height": 37,
      "confidence": 72.0,
      "level": 5,
      "page_num": 1,
      "block_num": 1,
      "par_num": 1,
      "line_num": 26,
      "word_num": 2
    },
    {
      "text": "High",
      "left": 1007,
      "top": 2849,
      "width": 57,
      "height": 28,
      "confidence": 93.0,
      "level": 5,
      "page_num": 1,
      "block_num": 1,
      "par_num": 1,
      "line_num": 26,
      "word_num": 3
    },
    {
      "text": "Critical,LC-Low",
      "left": 1075,
      "top": 2849,
      "width": 196,
      "height": 26,
      "confidence": 72.0,
      "level": 5,
      "page_num": 1,
      "block_num": 1,
      "par_num": 1,
      "line_num": 26,
      "word_num": 4
    },
    {
      "text": "Critical,C-Critical)",
      "left": 1281,
      "top": 2849,
      "width": 223,
      "height": 28,
      "confidence": 90.0,
      "level": 5,
      "page_num": 1,
      "block_num": 1,
      "par_num": 1,
      "line_num": 26,
      "word_num": 5
    },
    {
      "text": "Page",
      "left": 2069,
      "top": 2851,
      "width": 67,
      "height": 27,
      "confidence": 96.0,
      "level": 5,
      "page_num": 1,
      "block_num": 1,
      "par_num": 1,
      "line_num": 26,
      "word_num": 6
    },
    {
      "text": "1",
      "left": 2147,
      "top": 2851,
      "width": 10,
      "height": 21,
      "confidence": 94.0,
      "level": 5,
      "page_num": 1,
      "block_num": 1,
      "par_num": 1,
      "line_num": 26,
      "word_num": 7
    },
    {
      "text": "of",
      "left": 2170,
      "top": 2851,
      "width": 28,
      "height": 21,
      "confidence": 94.0,
      "level": 5,
      "page_num": 1,
      "block_num": 1,
      "par_num": 1,
      "line_num": 26,
      "word_num": 8
    },
    {
      "text": "3",
      "left": 2206,
      "top": 2851,
      "width": 14,
      "height": 21,
      "confidence": 95.0,
      "level": 5,
      "page_num": 1,
      "block_num": 1,
      "par_num": 1,
      "line_num": 26,
      "word_num": 9
    },
    {
      "text": "DR",
      "left": 232,
      "top": 3014,
      "width": 51,
      "height": 26,
      "confidence": 93.0,
      "level": 5,
      "page_num": 1,
      "block_num": 1,
      "par_num": 1,
      "line_num": 27,
      "word_num": 1
    },
    {
      "text": "Prajwal",
      "left": 297,
      "top": 3013,
      "width": 127,
      "height": 35,
      "confidence": 91.0,
      "level": 5,
      "page_num": 1,
      "block_num": 1,
      "par_num": 1,
      "line_num": 27,
      "word_num": 2
    },
    {
      "text": "A",
      "left": 438,
      "top": 3014,
      "width": 25,
      "height": 26,
      "confidence": 96.0,
      "level": 5,
      "page_num": 1,
      "block_num": 1,
      "par_num": 1,
      "line_num": 27,
      "word_num": 3
    },
    {
      "text": "HOD",
      "left": 232,
      "top": 3066,
      "width": 62,
      "height": 24,
      "confidence": 96.0,
      "level": 5,
      "page_num": 1,
      "block_num": 1,
      "par_num": 1,
      "line_num": 28,
      "word_num": 1
    },
    {
      "text": "Biochemistry",
      "left": 306,
      "top": 3065,
      "width": 174,
      "height": 31,
      "confidence": 96.0,
      "level": 5,
      "page_num": 1,
      "block_num": 1,
      "par_num": 1,
      "line_num": 28,
      "word_num": 2
    },
    {
      "text": "DLH",
      "left": 232,
      "top": 3104,
      "width": 54,
      "height": 23,
      "confidence": 90.0,
      "level": 5,
      "page_num": 1,
      "block_num": 1,
      "par_num": 1,
      "line_num": 29,
      "word_num": 1
    },
    {
      "text": "2018",
      "left": 299,
      "top": 3104,
      "width": 66,
      "height": 24,
      "confidence": 95.0,
      "level": 5,
      "page_num": 1,
      "block_num": 1,
      "par_num": 1,
      "line_num": 29,
      "word_num": 2
    },
    {
      "text": "0000588",
      "left": 377,
      "top": 3104,
      "width": 117,
      "height": 24,
      "confidence": 93.0,
      "level": 5,
      "page_num": 1,
      "block_num": 1,
      "par_num": 1,
      "line_num": 29,
      "word_num": 3
    },
    {
      "text": "KTK",
      "left": 507,
      "top": 3104,
      "width": 53,
      "height": 23,
      "confidence": 92.0,
      "level": 5,
      "page_num": 1,
      "block_num": 1,
      "par_num": 1,
      "line_num": 29,
      "word_num": 4
    },
    {
      "text": "Printed",
      "left": 1854,
      "top": 3161,
      "width": 97,
      "height": 21,
      "confidence": 95.0,
      "level": 5,
      "page_num": 1,
      "block_num": 1,
      "par_num": 1,
      "line_num": 30,
      "word_num": 1
    },
    {
      "text": "On:",
      "left": 1962,
      "top": 3162,
      "width": 47,
      "height": 20,
      "confidence": 90.0,
      "level": 5,
      "page_num": 1,
      "block_num": 1,
      "par_num": 1,
      "line_num": 30,
      "word_num": 2
    },
    {
      "text": "03-Jun-2025",
      "left": 2050,
      "top": 3161,
      "width": 162,
      "height": 22,
      "confidence": 90.0,
      "level": 5,
      "page_num": 1,
      "block_num": 1,
      "par_num": 1,
      "line_num": 30,
      "word_num": 3
    },
    {
      "text": "16:40",
      "left": 2223,
      "top": 3161,
      "width": 70,
      "height": 22,
      "confidence": 96.0,
      "level": 5,
      "page_num": 1,
      "block_num": 1,
      "par_num": 1,
      "line_num": 30,
      "word_num": 4
    },
    {
      "text": "Neuberg",
      "left": 308,
      "top": 3269,
      "width": 176,
      "height": 34,
      "confidence": 92.0,
      "level": 5,
      "page_num": 1,
      "block_num": 1,
      "par_num": 1,
      "line_num": 31,
      "word_num": 1
    },
    {
      "text": "Anand",
      "left": 505,
      "top": 3269,
      "width": 131,
      "height": 29,
      "confidence": 95.0,
      "level": 5,
      "page_num": 1,
      "block_num": 1,
      "par_num": 1,
      "line_num": 31,
      "word_num": 2
    },
    {
      "text": "Reference",
      "left": 659,
      "top": 3269,
      "width": 210,
      "height": 29,
      "confidence": 95.0,
      "level": 5,
      "page_num": 1,
      "block_num": 1,
      "par_num": 1,
      "line_num": 31,
      "word_num": 3
    },
    {
      "text": "Laboratory",
      "left": 890,
      "top": 3269,
      "width": 231,
      "height": 34,
      "confidence": 92.0,
      "level": 5,
      "page_num": 1,
      "block_num": 1,
      "par_num": 1,
      "line_num": 31,
      "word_num": 4
    },
    {
      "text": "-",
      "left": 1142,
      "top": 3283,
      "width": 12,
      "height": 5,
      "confidence": 91.0,
      "level": 5,
      "page_num": 1,
      "block_num": 1,
      "par_num": 1,
      "line_num": 31,
      "word_num": 5
    },
    {
      "text": "A",
      "left": 1174,
      "top": 3271,
      "width": 26,
      "height": 27,
      "confidence": 95.0,
      "level": 5,
      "page_num": 1,
      "block_num": 1,
      "par_num": 1,
      "line_num": 31,
      "word_num": 6
    },
    {
      "text": "Unit",
      "left": 1221,
      "top": 3269,
      "width": 83,
      "height": 29,
      "confidence": 95.0,
      "level": 5,
      "page_num": 1,
      "block_num": 1,
      "par_num": 1,
      "line_num": 31,
      "word_num": 7
    },
    {
      "text": "of",
      "left": 1324,
      "top": 3269,
      "width": 40,
      "height": 29,
      "confidence": 93.0,
      "level": 5,
      "page_num": 1,
      "block_num": 1,
      "par_num": 1,
      "line_num": 31,
      "word_num": 8
    },
    {
      "text": "Neuberg",
      "left": 1384,
      "top": 3269,
      "width": 177,
      "height": 34,
      "confidence": 92.0,
      "level": 5,
      "page_num": 1,
      "block_num": 1,
      "par_num": 1,
      "line_num": 31,
      "word_num": 9
    },
    {
      "text": "Diagnostics",
      "left": 1583,
      "top": 3269,
      "width": 246,
      "height": 34,
      "confidence": 96.0,
      "level": 5,
      "page_num": 1,
      "block_num": 1,
      "par_num": 1,
      "line_num": 31,
      "word_num": 10
    },
    {
      "text": "Private",
      "left": 1851,
      "top": 3269,
      "width": 146,
      "height": 29,
      "confidence": 95.0,
      "level": 5,
      "page_num": 1,
      "block_num": 1,
      "par_num": 1,
      "line_num": 31,
      "word_num": 11
    },
    {
      "text": "Limited",
      "left": 2018,
      "top": 3269,
      "width": 156,
      "height": 29,
      "confidence": 95.0,
      "level": 5,
      "page_num": 1,
      "block_num": 1,
      "par_num": 1,
      "line_num": 31,
      "word_num": 12
    },
    {
      "text": "Laboratory",
      "left": 203,
      "top": 3328,
      "width": 189,
      "height": 31,
      "confidence": 92.0,
      "level": 5,
      "page_num": 1,
      "block_num": 1,
      "par_num": 1,
      "line_num": 32,
      "word_num": 1
    },
    {
      "text": ":",
      "left": 407,
      "top": 3335,
      "width": 5,
      "height": 19,
      "confidence": 90.0,
      "level": 5,
      "page_num": 1,
      "block_num": 1,
      "par_num": 1,
      "line_num": 32,
      "word_num": 2
    },
    {
      "text": "#54,",
      "left": 427,
      "top": 3329,
      "width": 74,
      "height": 28,
      "confidence": 96.0,
      "level": 5,
      "page_num": 1,
      "block_num": 1,
      "par_num": 1,
      "line_num": 32,
      "word_num": 3
    },
    {
      "text": "Anand",
      "left": 516,
      "top": 3328,
      "width": 108,
      "height": 26,
      "confidence": 96.0,
      "level": 5,
      "page_num": 1,
      "block_num": 1,
      "par_num": 1,
      "line_num": 32,
      "word_num": 4
    },
    {
      "text": "Tower,",
      "left": 640,
      "top": 3329,
      "width": 105,
      "height": 27,
      "confidence": 95.0,
      "level": 5,
      "page_num": 1,
      "block_num": 1,
      "par_num": 1,
      "line_num": 32,
      "word_num": 5
    },
    {
      "text": "Bowring",
      "left": 761,
      "top": 3329,
      "width": 138,
      "height": 30,
      "confidence": 96.0,
      "level": 5,
      "page_num": 1,
      "block_num": 1,
      "par_num": 1,
      "line_num": 32,
      "word_num": 6
    },
    {
      "text": "Hospital",
      "left": 916,
      "top": 3328,
      "width": 136,
      "height": 31,
      "confidence": 95.0,
      "level": 5,
      "page_num": 1,
      "block_num": 1,
      "par_num": 1,
      "line_num": 32,
      "word_num": 7
    },
    {
      "text": "Road,",
      "left": 1070,
      "top": 3328,
      "width": 93,
      "height": 29,
      "confidence": 96.0,
      "level": 5,
      "page_num": 1,
      "block_num": 1,
      "par_num": 1,
      "line_num": 32,
      "word_num": 8
    },
    {
      "text": "Read.",
      "left": 1319,
      "top": 3328,
      "width": 95,
      "height": 31,
      "confidence": 82.0,
      "level": 5,
      "page_num": 1,
      "block_num": 1,
      "par_num": 1,
      "line_num": 32,
      "word_num": 9
    },
    {
      "text": "Office",
      "left": 1431,
      "top": 3328,
      "width": 100,
      "height": 26,
      "confidence": 91.0,
      "level": 5,
      "page_num": 1,
      "block_num": 1,
      "par_num": 1,
      "line_num": 32,
      "word_num": 10
    },
    {
      "text": ":",
      "left": 1546,
      "top": 3335,
      "width": 5,
      "height": 19,
      "confidence": 84.0,
      "level": 5,
      "page_num": 1,
      "block_num": 1,
      "par_num": 1,
      "line_num": 32,
      "word_num": 11
    },
    {
      "text": "Plot",
      "left": 1568,
      "top": 3328,
      "width": 65,
      "height": 26,
      "confidence": 96.0,
      "level": 5,
      "page_num": 1,
      "block_num": 1,
      "par_num": 1,
      "line_num": 32,
      "word_num": 12
    },
    {
      "text": "No.",
      "left": 1649,
      "top": 3329,
      "width": 51,
      "height": 25,
      "confidence": 95.0,
      "level": 5,
      "page_num": 1,
      "block_num": 1,
      "par_num": 1,
      "line_num": 32,
      "word_num": 13
    },
    {
      "text": "7,",
      "left": 1716,
      "top": 3329,
      "width": 21,
      "height": 28,
      "confidence": 95.0,
      "level": 5,
      "page_num": 1,
      "block_num": 1,
      "par_num": 1,
      "line_num": 32,
      "word_num": 14
    },
    {
      "text": "Industrial",
      "left": 1754,
      "top": 3328,
      "width": 155,
      "height": 26,
      "confidence": 94.0,
      "level": 5,
      "page_num": 1,
      "block_num": 1,
      "par_num": 1,
      "line_num": 32,
      "word_num": 15
    },
    {
      "text": "Estate,",
      "left": 1927,
      "top": 3329,
      "width": 112,
      "height": 28,
      "confidence": 95.0,
      "level": 5,
      "page_num": 1,
      "block_num": 1,
      "par_num": 1,
      "line_num": 32,
      "word_num": 16
    },
    {
      "text": "Rajiv",
      "left": 2055,
      "top": 3329,
      "width": 79,
      "height": 30,
      "confidence": 95.0,
      "level": 5,
      "page_num": 1,
      "block_num": 1,
      "par_num": 1,
      "line_num": 32,
      "word_num": 17
    },
    {
      "text": "Gandhi",
      "left": 2149,
      "top": 3328,
      "width": 118,
      "height": 26,
      "confidence": 93.0,
      "level": 5,
      "page_num": 1,
      "block_num": 1,
      "par_num": 1,
      "line_num": 32,
      "word_num": 18
    },
    {
      "text": "Salai,",
      "left": 2284,
      "top": 3328,
      "width": 85,
      "height": 29,
      "confidence": 93.0,
      "level": 5,
      "page_num": 1,
      "block_num": 1,
      "par_num": 1,
      "line_num": 32,
      "word_num": 19
    },
    {
      "text": "Shivajinagar,",
      "left": 308,
      "top": 3368,
      "width": 212,
      "height": 31,
      "confidence": 89.0,
      "level": 5,
      "page_num": 1,
      "block_num": 1,
      "par_num": 1,
      "line_num": 33,
      "word_num": 1
    },
    {
      "text": "Bangalore-560",
      "left": 537,
      "top": 3369,
      "width": 253,
      "height": 30,
      "confidence": 67.0,
      "level": 5,
      "page_num": 1,
      "block_num": 1,
      "par_num": 1,
      "line_num": 33,
      "word_num": 2
    },
    {
      "text": "001",
      "left": 805,
      "top": 3369,
      "width": 57,
      "height": 25,
      "confidence": 83.0,
      "level": 5,
      "page_num": 1,
      "block_num": 1,
      "par_num": 1,
      "line_num": 33,
      "word_num": 3
    },
    {
      "text": "°1800",
      "left": 905,
      "top": 3368,
      "width": 96,
      "height": 27,
      "confidence": 66.0,
      "level": 5,
      "page_num": 1,
      "block_num": 1,
      "par_num": 1,
      "line_num": 33,
      "word_num": 4
    },
    {
      "text": "425",
      "left": 1016,
      "top": 3369,
      "width": 61,
      "height": 25,
      "confidence": 96.0,
      "level": 5,
      "page_num": 1,
      "block_num": 1,
      "par_num": 1,
      "line_num": 33,
      "word_num": 5
    },
    {
      "text": "1974",
      "left": 1092,
      "top": 3369,
      "width": 72,
      "height": 25,
      "confidence": 95.0,
      "level": 5,
      "page_num": 1,
      "block_num": 1,
      "par_num": 1,
      "line_num": 33,
      "word_num": 6
    },
    {
      "text": "Perungudi,",
      "left": 1319,
      "top": 3368,
      "width": 180,
      "height": 31,
      "confidence": 92.0,
      "level": 5,
      "page_num": 1,
      "block_num": 1,
      "par_num": 1,
      "line_num": 33,
      "word_num": 7
    },
    {
      "text": "Chennai",
      "left": 1515,
      "top": 3368,
      "width": 134,
      "height": 26,
      "confidence": 90.0,
      "level": 5,
      "page_num": 1,
      "block_num": 1,
      "par_num": 1,
      "line_num": 33,
      "word_num": 8
    },
    {
      "text": "-",
      "left": 1665,
      "top": 3381,
      "width": 11,
      "height": 3,
      "confidence": 90.0,
      "level": 5,
      "page_num": 1,
      "block_num": 1,
      "par_num": 1,
      "line_num": 33,
      "word_num": 9
    },
    {
      "text": "600096,",
      "left": 1691,
      "top": 3369,
      "width": 145,
      "height": 27,
      "confidence": 96.0,
      "level": 5,
      "page_num": 1,
      "block_num": 1,
      "par_num": 1,
      "line_num": 33,
      "word_num": 10
    },
    {
      "text": "Tamil",
      "left": 1850,
      "top": 3368,
      "width": 87,
      "height": 26,
      "confidence": 96.0,
      "level": 5,
      "page_num": 1,
      "block_num": 1,
      "par_num": 1,
      "line_num": 33,
      "word_num": 11
    },
    {
      "text": "Nadu,",
      "left": 1954,
      "top": 3368,
      "width": 95,
      "height": 29,
      "confidence": 96.0,
      "level": 5,
      "page_num": 1,
      "block_num": 1,
      "par_num": 1,
      "line_num": 33,
      "word_num": 12
    },
    {
      "text": "India.",
      "left": 2066,
      "top": 3368,
      "width": 87,
      "height": 26,
      "confidence": 90.0,
      "level": 5,
      "page_num": 1,
      "block_num": 1,
      "par_num": 1,
      "line_num": 33,
      "word_num": 13
    },
    {
      "text": "enquiry‘@neuberganand.com",
      "left": 672,
      "top": 3408,
      "width": 491,
      "height": 31,
      "confidence": 24.0,
      "level": 5,
      "page_num": 1,
      "block_num": 1,
      "par_num": 1,
      "line_num": 34,
      "word_num": 2
    },
    {
      "text": "“www.neubergdiagnostics.com",
      "left": 1329,
      "top": 3408,
      "width": 535,
      "height": 31,
      "confidence": 50.0,
      "level": 5,
      "page_num": 1,
      "block_num": 1,
      "par_num": 1,
      "line_num": 34,
      "word_num": 3
    }
  ]
}