{
  "patient_info": {
    "name": "to change from mild to severe in COVID positive"
  },
  "test_results": [
    {
      "test_name": "ABSOLUTE BASOPHIL COUNT",
      "value": "0",
      "unit": "Low",
      "confidence": 90.0,
      "line_number": 34
    },
    {
      "test_name": "Tel",
      "value": "9111591115,",
      "unit": "Fax",
      "confidence": 90.0,
      "line_number": 78
    }
  ],
  "other_fields": {
    "doctor": "A i"
  },
  "confidence_scores": {
    "name": 95.04
  },
  "page": 44,
  "extraction_methods": {
    "ml_model_used": true,
    "rule_based_used": true,
    "ml_entities_found": 0,
    "rule_entities_found": 1
  }
}